economy/__init__.py
economy-0.0.1.dist-info/METADATA
economy-0.0.1.dist-info/WHEEL
economy-0.0.1.dist-info/top_level.txt
economy-0.0.1.dist-info/RECORD
