Metadata-Version: 2.1
Name: economy
Version: 0.0.1
Summary: Utility library for Apache Arrow Flight & Flight SQL servers
Author-email: Alex Kwiatkowski <alex+pypi@fremantle.io>
License: MIT License
Project-URL: Homepage, https://github.com/rupurt/economy
Project-URL: Issues, https://github.com/rupurt/economy/issues
Classifier: Programming Language :: Python :: 3
Classifier: Operating System :: OS Independent
Requires-Python: >=3.12
Requires-Dist: pyarrow[flight] ==19.0.*
